malaffinity/__about__.py
malaffinity/__init__.py
malaffinity/calcs.py
malaffinity/const.py
malaffinity/endpoints.py
malaffinity/exceptions.py
malaffinity/malaffinity.py
malaffinity/models.py
malaffinity-2.5.2.dist-info/DESCRIPTION.rst
malaffinity-2.5.2.dist-info/METADATA
malaffinity-2.5.2.dist-info/RECORD
malaffinity-2.5.2.dist-info/WHEEL
malaffinity-2.5.2.dist-info/metadata.json
malaffinity-2.5.2.dist-info/top_level.txt
