Metadata-Version: 2.0
Name: malaffinity
Version: 2.5.2
Summary: Calculate affinity between MyAnimeList users
Home-page: https://github.com/erkghlerngm44/malaffinity
Author: erkghlerngm44
Author-email: erkghlerngm44@protonmail.com
License: MIT
Keywords: myanimelist affinity mal
Platform: UNKNOWN
Classifier: Development Status :: 5 - Production/Stable
Classifier: Intended Audience :: Developers
Classifier: Topic :: Software Development
Classifier: Operating System :: OS Independent
Classifier: License :: OSI Approved :: MIT License
Classifier: Programming Language :: Python :: 2
Classifier: Programming Language :: Python :: 2.7
Classifier: Programming Language :: Python :: 3
Classifier: Programming Language :: Python :: 3.4
Classifier: Programming Language :: Python :: 3.5
Classifier: Programming Language :: Python :: 3.6
Requires-Dist: beautifulsoup4 (<5,>=4.6)
Requires-Dist: lxml (<4,>=3.8)
Requires-Dist: requests (<3,>=2.18)
Requires-Dist: statistics (<2,>=1.0)
Provides-Extra: conventions
Requires-Dist: flake8 (<4,>=3.4); extra == 'conventions'
Requires-Dist: pydocstyle (<3,>=2.0); extra == 'conventions'
Provides-Extra: docs
Requires-Dist: sphinx (<2,>=1.6); extra == 'docs'
Requires-Dist: sphinx-rtd-theme; extra == 'docs'
Provides-Extra: tests
Requires-Dist: coverage (<5,>=4.4); extra == 'tests'
Requires-Dist: mock (<3,>=2.0); extra == 'tests'
Requires-Dist: pytest (<4,>=3.1); extra == 'tests'
Requires-Dist: vcrpy (<2,>=1.11); extra == 'tests'
Provides-Extra: travis
Requires-Dist: codecov (<3,>=2.0); extra == 'travis'
